direct_redis/__init__.py
direct_redis/direct_redis.py
direct_redis/functions.py
direct_redis-0.3.1.dist-info/LICENSE
direct_redis-0.3.1.dist-info/METADATA
direct_redis-0.3.1.dist-info/WHEEL
direct_redis-0.3.1.dist-info/top_level.txt
direct_redis-0.3.1.dist-info/RECORD
