Metadata-Version: 2.1
Name: direct-redis
Version: 0.3.1
Summary: Serialize any python datatypes and does redis actions using redis-py
Home-page: https://github.com/yonghee12/direct-redis
Author: Yonghee Cheon
Author-email: yonghee.cheon@gmail.com
License: MIT
Platform: UNKNOWN
Classifier: Programming Language :: Python :: 3
Classifier: License :: OSI Approved :: MIT License
Classifier: Operating System :: OS Independent
Requires-Python: >=3.4
Requires-Dist: redis (==3.4.1)
